{
  "version": "1.0.0",
  "timestamp": 1710240006000,
  "description": "Right-angle triangle",
  "expectedShape": "triangle",
  "canvasState": {
    "strokes": [
      {
        "id": "baseline_triangle_right_001",
        "points": [
          {"x": 50, "y": 50, "timestamp": 1000},
          {"x": 50, "y": 55, "timestamp": 1016},
          {"x": 50, "y": 60, "timestamp": 1032},
          {"x": 50, "y": 65, "timestamp": 1048},
          {"x": 50, "y": 70, "timestamp": 1064},
          {"x": 50, "y": 75, "timestamp": 1080},
          {"x": 50, "y": 80, "timestamp": 1096},
          {"x": 50, "y": 85, "timestamp": 1112},
          {"x": 50, "y": 90, "timestamp": 1128},
          {"x": 50, "y": 95, "timestamp": 1144},
          {"x": 50, "y": 100, "timestamp": 1160},
          {"x": 50, "y": 105, "timestamp": 1176},
          {"x": 50, "y": 110, "timestamp": 1192},
          {"x": 50, "y": 115, "timestamp": 1208},
          {"x": 50, "y": 120, "timestamp": 1224},
          {"x": 50, "y": 125, "timestamp": 1240},
          {"x": 50, "y": 130, "timestamp": 1256},
          {"x": 50, "y": 135, "timestamp": 1272},
          {"x": 50, "y": 140, "timestamp": 1288},
          {"x": 50, "y": 145, "timestamp": 1304},
          {"x": 50, "y": 150, "timestamp": 1320},
          {"x": 55, "y": 150, "timestamp": 1336},
          {"x": 60, "y": 150, "timestamp": 1352},
          {"x": 65, "y": 150, "timestamp": 1368},
          {"x": 70, "y": 150, "timestamp": 1384},
          {"x": 75, "y": 150, "timestamp": 1400},
          {"x": 80, "y": 150, "timestamp": 1416},
          {"x": 85, "y": 150, "timestamp": 1432},
          {"x": 90, "y": 150, "timestamp": 1448},
          {"x": 95, "y": 150, "timestamp": 1464},
          {"x": 100, "y": 150, "timestamp": 1480},
          {"x": 105, "y": 150, "timestamp": 1496},
          {"x": 110, "y": 150, "timestamp": 1512},
          {"x": 115, "y": 150, "timestamp": 1528},
          {"x": 120, "y": 150, "timestamp": 1544},
          {"x": 125, "y": 150, "timestamp": 1560},
          {"x": 130, "y": 150, "timestamp": 1576},
          {"x": 135, "y": 150, "timestamp": 1592},
          {"x": 140, "y": 150, "timestamp": 1608},
          {"x": 145, "y": 150, "timestamp": 1624},
          {"x": 150, "y": 150, "timestamp": 1640},
          {"x": 145, "y": 145, "timestamp": 1656},
          {"x": 140, "y": 140, "timestamp": 1672},
          {"x": 135, "y": 135, "timestamp": 1688},
          {"x": 130, "y": 130, "timestamp": 1704},
          {"x": 125, "y": 125, "timestamp": 1720},
          {"x": 120, "y": 120, "timestamp": 1736},
          {"x": 115, "y": 115, "timestamp": 1752},
          {"x": 110, "y": 110, "timestamp": 1768},
          {"x": 105, "y": 105, "timestamp": 1784},
          {"x": 100, "y": 100, "timestamp": 1800},
          {"x": 95, "y": 95, "timestamp": 1816},
          {"x": 90, "y": 90, "timestamp": 1832},
          {"x": 85, "y": 85, "timestamp": 1848},
          {"x": 80, "y": 80, "timestamp": 1864},
          {"x": 75, "y": 75, "timestamp": 1880},
          {"x": 70, "y": 70, "timestamp": 1896},
          {"x": 65, "y": 65, "timestamp": 1912},
          {"x": 60, "y": 60, "timestamp": 1928},
          {"x": 55, "y": 55, "timestamp": 1944},
          {"x": 50, "y": 50, "timestamp": 1960}
        ],
        "smoothedPoints": [
          {"x": 50, "y": 50},
          {"x": 50, "y": 150},
          {"x": 150, "y": 150},
          {"x": 50, "y": 50}
        ],
        "color": "#000000",
        "thickness": 2,
        "timestamp": 1000,
        "strokeType": "artistic"
      }
    ],
    "canvasWidth": 200,
    "canvasHeight": 200,
    "zoom": 1,
    "panX": 0,
    "panY": 0,
    "strokeMode": "original"
  }
}
